guicalculator/__init__.py
guicalculator/__main__.py
guicalculator/buttoncfg.py
guicalculator/calculator/__init__.py
guicalculator/calculator/calculatordata/__init__.py
guicalculator/calculator/calculatordata/calculatordata.py
guicalculator/calculator/calculatordata/functions/__init__.py
guicalculator/calculator/calculatordata/functions/displaycalc.py
guicalculator/calculator/calculatordata/functions/evalcalc.py
guicalculator/calculator/calculatordata/functions/getuservar.py
guicalculator/calculator/calculatordata/functions/processbutton.py
guicalculator/calculator/calculatordata/functions/setuservar.py
guicalculator/calculator/calculatordata/private/__init__.py
guicalculator/calculator/calculatordata/private/backspace.py
guicalculator/calculator/calculatordata/private/buttonpress.py
guicalculator/calculator/calculatordata/private/calculate.py
guicalculator/calculator/calculatordata/private/clearall.py
guicalculator/calculator/calculatordata/private/clearvalue.py
guicalculator/calculator/calculatordata/private/getcurinpt.py
guicalculator/calculator/calculatordata/private/getmem.py
guicalculator/calculator/calculatordata/private/getnumfncsym.py
guicalculator/calculator/calculatordata/private/getuservarnames.py
guicalculator/calculator/calculatordata/private/invnum.py
guicalculator/calculator/calculatordata/private/memadd.py
guicalculator/calculator/calculatordata/private/memclear.py
guicalculator/calculator/calculatordata/private/memrecall.py
guicalculator/calculator/calculatordata/private/memstore.py
guicalculator/calculator/calculatordata/private/memswap.py
guicalculator/calculator/calculatordata/private/negate.py
guicalculator/calculator/calculatordata/private/rootnum.py
guicalculator/calculator/calculatordata/private/squarenum.py
guicalculator/calculator/calculatordata/private/types.py
guicalculator/calculator/calculatordata/private/updatecalc.py
guicalculator/calculator/calculatordata/private/validatesymfunc.py
guicalculator/calculator/evaluate_calculation.py
guicalculator-0.1.3.dist-info/entry_points.txt
guicalculator-0.1.3.dist-info/LICENSE
guicalculator-0.1.3.dist-info/METADATA
guicalculator-0.1.3.dist-info/WHEEL
guicalculator-0.1.3.dist-info/RECORD
