Metadata-Version: 2.1
Name: guicalculator
Version: 0.1.3
Summary: A calculator written with python and tkinter
Home-page: https://github.com/tombroth/guicalculator
License: MIT
Author: Thomas Brotherton
Author-email: tombroth@gmail.com
Requires-Python: >=3.12,<4.0
Classifier: License :: OSI Approved :: MIT License
Classifier: Operating System :: OS Independent
Classifier: Programming Language :: Python :: 3
Classifier: Programming Language :: Python :: 3.12
Project-URL: Repository, https://github.com/tombroth/guicalculator
